PluginsPy/CmdSets.py
PluginsPy/Config.py
PluginsPy/DataLive.py
PluginsPy/MainUI.py
PluginsPy/Perf.py
PluginsPy/Plugin.py
PluginsPy/PluginProcess.py
PluginsPy/PluginTemplate.py
PluginsPy/Tools.py
PluginsPy/VisualLogPlot.py
PluginsPy/__init__.py
PluginsPy/assets/PluginTemplate.py
PluginsPy/assets/images/icon.png
PluginsPy/template/Makefile
PluginsPy/template/main.py
PluginsPy/template/make.bat
PluginsPy/template/CmdSets/0001_Android.json
PluginsPy/template/Plugins/0001_PluginExample.py
PluginsPy/template/Plugins/0002_AndroidSystemWakeup.py
PluginsPy/template/Plugins/0003_MediaPipeHands.py
PluginsPy/template/Plugins/0004_KernelKey.py
PluginsPy/template/Plugins/0005_KernelKeyDiff.py
PluginsPy/template/Plugins/0006_KernelKeyLoop.py
PluginsPy/template/Plugins/PluginExample.py
PluginsPy/template/Plugins/__init__.py
PluginsPy/template/input/0002_AndroidSystemWakeup.curf
PluginsPy/template/input/0003_hands.txt
PluginsPy/template/input/0004_kernel_1.txt
PluginsPy/template/input/0004_kernel_2.txt
PluginsPy/template/input/0005_kernel_1_keydiff.txt
PluginsPy/template/input/0005_kernel_2_keydiff.txt
pluginspy-0.2.20.dist-info/LICENSE
pluginspy-0.2.20.dist-info/METADATA
pluginspy-0.2.20.dist-info/WHEEL
pluginspy-0.2.20.dist-info/entry_points.txt
pluginspy-0.2.20.dist-info/top_level.txt
pluginspy-0.2.20.dist-info/RECORD
