Metadata-Version: 2.1
Name: pluginspy
Version: 0.2.20
Summary: Plugins Framework
Home-page: https://github.com/FolderLevel/PluginsPy
Author: zengjf
Author-email: zengjf42@163.com
License: UNKNOWN
Project-URL: Bug Tracker, https://github.com/FolderLevel/PluginsPy/issues
Platform: UNKNOWN
Classifier: Programming Language :: Python :: 3
Classifier: License :: OSI Approved :: MIT License
Classifier: Operating System :: OS Independent
Requires-Python: >=3.0
License-File: LICENSE
Requires-Dist: PyQt5
Requires-Dist: VisualLog (>=0.0.16)
Requires-Dist: windows-curses ; platform_system == "Windows"
